scutls/__init__.py
scutls/arguments.py
scutls/assets/genome_ensembl_107_54_54_54.json
scutls/assets/genome_ensembl_release_all.txt
scutls/assets/genome_ensembl_release_use.txt
scutls/assets/genome_ucsc.json
scutls/bam.py
scutls/barcode.py
scutls/cli.py
scutls/download.py
scutls/fastq.py
scutls/util.py
scutls-0.3.3.dist-info/entry_points.txt
scutls-0.3.3.dist-info/WHEEL
scutls-0.3.3.dist-info/METADATA
scutls-0.3.3.dist-info/RECORD
